llx/__init__.py
llx/cli.py
llx/crawler.py
llx/plugin_manager.py
llx/pricing_manager.py
llx/response_judge.py
llx/server.py
llx/utils.py
llx/commands/__init__.py
llx/commands/benchmark_command.py
llx/commands/chat_command.py
llx/commands/files_to_prompt_command.py
llx/commands/list_models_command.py
llx/commands/plugin_command.py
llx/commands/prompt_command.py
llx/commands/server_command.py
llx/commands/url_to_prompt_command.py
llx/plugins/__init__.py
llx/plugins/base_plugin.py
llx/plugins/builtin/__init__.py
llx/plugins/builtin/template_plugin.py
llx/providers/__init__.py
llx/providers/anthropic_provider.py
llx/providers/deepseek_provider.py
llx/providers/gemini_provider.py
llx/providers/mistral_provider.py
llx/providers/ollama_provider.py
llx/providers/openai_provider.py
llx/providers/perplexity_provider.py
llx/providers/provider.py
llx/providers/xai_provider.py
llm_cli_tools-0.3.0.dist-info/METADATA
llm_cli_tools-0.3.0.dist-info/WHEEL
llm_cli_tools-0.3.0.dist-info/entry_points.txt
llm_cli_tools-0.3.0.dist-info/top_level.txt
llm_cli_tools-0.3.0.dist-info/RECORD
